awget/__init__.py
awget/__main__.py
awget/main.py
awget-0.0.9.dist-info/METADATA
awget-0.0.9.dist-info/WHEEL
awget-0.0.9.dist-info/licenses/LICENSE
awget-0.0.9.dist-info/RECORD
