Metadata-Version: 2.4
Name: awget
Version: 0.0.9
Summary: Pure python download utility can batch download of files listed based on a certain URL
Project-URL: Homepage, https://github.com/breezecloud/awget
Project-URL: Issues, https://github.com/breezecloud/awget/issues
Author-email: luping <luping.sh@chinatelecom.cn>
License: Copyright (c) 2021 The Python Packaging Authority
License-File: LICENSE
Classifier: Operating System :: OS Independent
Classifier: Programming Language :: Python :: 3
Requires-Python: >=3.0
Requires-Dist: pyquery>=2.0.1
Requires-Dist: pywin32>=306; os_name == 'nt'
Requires-Dist: requests>=2.32.3
